MANIFEST.in
requirements.txt
setup.py
vialink/utils/pubsub/__init__.py
vialink/utils/pubsub/pubsub.py
vialink/utils/pubsub/settings.py
vialink_utils_pubsub.egg-info/PKG-INFO
vialink_utils_pubsub.egg-info/SOURCES.txt
vialink_utils_pubsub.egg-info/dependency_links.txt
vialink_utils_pubsub.egg-info/requires.txt
vialink_utils_pubsub.egg-info/top_level.txt