Metadata-Version: 1.2
Name: vialink-utils-pubsub
Version: 0.0.1
Summary: ViaLink Utils PubSub
Home-page: UNKNOWN
Author: SSripilaipong
Author-email: santhapon.s@siametrics.com
License: Apache 2.0
Platform: UNKNOWN
Requires-Python: >=3.7
